<?xml version="1.0" encoding="ISO-8859-1"?>
<resources>
<resource value="1879048666" identifier="Lore_of_the_Blade"/>
<resource value="1879048669" identifier="The_Book_of_Beasts"/>
<resource value="1879048670" identifier="Of_Leaf_and_Twig"/>
<resource value="1879048690" identifier="Melodies_of_the_Valar"/>
<resource value="1879048691" identifier="The_Rising_Chord"/>
<resource value="1879048692" identifier="Valour%27s_Marches"/>
<resource value="1879048703" identifier="The_Book_of_Knives"/>
<resource value="1879048704" identifier="Knee-breaker%27s_Manual"/>
<resource value="1879048705" identifier="The_Expert%27s_Guide_to_Dirty_Fighting"/>
<resource value="1879051515" identifier="The_Life_of_a_Bounder_(final)"/>
<resource value="1879051519" identifier="The_Life_of_a_Bounder_(advanced)"/>
<resource value="1879051521" identifier="The_Life_of_a_Bounder"/>
<resource value="1879051827" identifier="Swift_and_Subtle"/>
<resource value="1879051829" identifier="Hidden_Dagger"/>
<resource value="1879051832" identifier="Focused_Eye"/>
<resource value="1879051833" identifier="Side-step"/>
<resource value="1879051834" identifier="Trickster"/>
<resource value="1879051837" identifier="Strike_from_Shadows"/>
<resource value="1879051838" identifier="Footpad"/>
<resource value="1879051839" identifier="Disabling_Attack"/>
<resource value="1879051840" identifier="Opportunist"/>
<resource value="1879051841" identifier="Overwhelming_Odds"/>
<resource value="1879051842" identifier="Leaf-walker"/>
<resource value="1879051843" identifier="Blind_Fury"/>
<resource value="1879051845" identifier="Alert_Guard_(Class)"/>
<resource value="1879051846" identifier="Turn_of_the_Tide"/>
<resource value="1879051847" identifier="Renewed_Voice"/>
<resource value="1879051850" identifier="Captain%27s_Valour"/>
<resource value="1879051852" identifier="Strong_Voice"/>
<resource value="1879051854" identifier="Captain%27s_Hope"/>
<resource value="1879051855" identifier="Expert_Attacks"/>
<resource value="1879051858" identifier="Captain%27s_Victory"/>
<resource value="1879051883" identifier="Stinging_Blow"/>
<resource value="1879051884" identifier="Reactive_Block"/>
<resource value="1879051885" identifier="Guardian%27s_Ward"/>
<resource value="1879051886" identifier="Shield_Expertise"/>
<resource value="1879051888" identifier="Controlled_Breathing"/>
<resource value="1879051889" identifier="Harasser"/>
<resource value="1879051890" identifier="To_the_Rescue"/>
<resource value="1879051892" identifier="Quickness"/>
<resource value="1879051893" identifier="Grim_Challenge"/>
<resource value="1879051894" identifier="Selfless_Defence"/>
<resource value="1879051895" identifier="Stoic"/>
<resource value="1879051896" identifier="Strong_Lungs"/>
<resource value="1879051897" identifier="Brave_Heart"/>
<resource value="1879051898" identifier="Heat_of_Battle"/>
<resource value="1879051900" identifier="Sturdy_Traps"/>
<resource value="1879051901" identifier="Rapid_Recovery"/>
<resource value="1879051902" identifier="Barbed_Fury"/>
<resource value="1879051903" identifier="Swift_and_True"/>
<resource value="1879051905" identifier="Strong_Draw"/>
<resource value="1879051906" identifier="Heightened_Senses"/>
<resource value="1879051907" identifier="Hail_of_Arrows"/>
<resource value="1879051909" identifier="Arrow-storm"/>
<resource value="1879051910" identifier="Deep_Concentration"/>
<resource value="1879051911" identifier="Deadly_Precision"/>
<resource value="1879051912" identifier="True_Shot"/>
<resource value="1879051913" identifier="Springloaded_Traps"/>
<resource value="1879051914" identifier="Stealthy_Shot"/>
<resource value="1879051915" identifier="Swift_Recovery"/>
<resource value="1879051917" identifier="Master_of_the_Staff"/>
<resource value="1879051918" identifier="Power_and_Wisdom"/>
<resource value="1879051919" identifier="Light_of_Hope"/>
<resource value="1879051920" identifier="Master_of_Beasts"/>
<resource value="1879051922" identifier="Deep_Lore"/>
<resource value="1879051923" identifier="Healer"/>
<resource value="1879051924" identifier="Beast-lore"/>
<resource value="1879051926" identifier="D%C3%BAnadan-learning"/>
<resource value="1879051927" identifier="Harmony_with_Nature"/>
<resource value="1879051928" identifier="Awareness_of_Body"/>
<resource value="1879051929" identifier="Subtlety_of_Wisdom"/>
<resource value="1879051930" identifier="Proof_against_all_Ills"/>
<resource value="1879051931" identifier="Knowledge_of_the_Past"/>
<resource value="1879051932" identifier="Magic_Adept"/>
<resource value="1879051934" identifier="Harmonious_Melody"/>
<resource value="1879051935" identifier="Herald%27s_Hammer"/>
<resource value="1879051936" identifier="Smooth_Voice"/>
<resource value="1879051937" identifier="Powerful_Voice"/>
<resource value="1879051939" identifier="Life-singer"/>
<resource value="1879051940" identifier="Unrelenting"/>
<resource value="1879051941" identifier="Focused_Performance"/>
<resource value="1879051943" identifier="Light_in_the_Dark"/>
<resource value="1879051944" identifier="Graceful_Demeanour"/>
<resource value="1879051945" identifier="Silver_Tongue"/>
<resource value="1879051946" identifier="Subtle_Movements"/>
<resource value="1879051947" identifier="Strength_of_Voice"/>
<resource value="1879051948" identifier="Battle-hymn"/>
<resource value="1879051949" identifier="Heralded_Saviour"/>
<resource value="1879052485" identifier="A_Shot_in_the_Dark"/>
<resource value="1879052486" identifier="The_Way_of_the_Hunter"/>
<resource value="1879052487" identifier="The_Furthest_Charge"/>
<resource value="1879053012" identifier="The_Candle%27s_Flame"/>
<resource value="1879053014" identifier="The_Book_of_Oaths"/>
<resource value="1879060151" identifier="The_Best_Defence"/>
<resource value="1879060152" identifier="A_Shield-maiden%27s_Song"/>
<resource value="1879060153" identifier="The_Final_Word"/>
<resource value="1879071632" identifier="Fire-breather"/>
<resource value="1879071634" identifier="Hero"/>
<resource value="1879071646" identifier="The_Wary"/>
<resource value="1879071647" identifier="The_Undefeated"/>
<resource value="1879071648" identifier="The_Indomitable"/>
<resource value="1879071649" identifier="The_Unscathed"/>
<resource value="1879071650" identifier="The_Undying"/>
<resource value="1879071651" identifier="The_High_Passes"/>
<resource value="1879071652" identifier="Ruins_of_the_Misty_Mountains"/>
<resource value="1879071653" identifier="Where_Giants_Dwell"/>
<resource value="1879071654" identifier="The_Road_to_Rivendell"/>
<resource value="1879071655" identifier="Ruins_of_the_Trollshaws"/>
<resource value="1879071656" identifier="Scouting_the_Dourhands"/>
<resource value="1879071657" identifier="Places_of_the_Dwarves"/>
<resource value="1879071658" identifier="Elf-ruins_Exploration"/>
<resource value="1879071659" identifier="Rath_Teraig_Exploration"/>
<resource value="1879071660" identifier="The_Villages_of_the_Earth-kin"/>
<resource value="1879071661" identifier="The_Eastern_Ruins"/>
<resource value="1879071663" identifier="The_Western_Ruins"/>
<resource value="1879071664" identifier="Garth_Agarwen_Exploration"/>
<resource value="1879071665" identifier="The_Grimfens"/>
<resource value="1879071666" identifier="Defences_of_the_Lone-lands"/>
<resource value="1879071667" identifier="Weathertop_Exploration"/>
<resource value="1879071668" identifier="The_Farms_of_the_Shire"/>
<resource value="1879071669" identifier="The_Sights_of_the_Shire"/>
<resource value="1879071670" identifier="The_Barrow-downs"/>
<resource value="1879071671" identifier="The_Old_Forest"/>
<resource value="1879071672" identifier="The_Ruins_of_Breeland"/>
<resource value="1879071673" identifier="Lore_of_the_Cardolan_Prince"/>
<resource value="1879071674" identifier="The_History_of_the_D%C3%BAnedain"/>
<resource value="1879071675" identifier="Flowers_of_the_Old_Forest"/>
<resource value="1879071676" identifier="Bree-land_Adventurer"/>
<resource value="1879071677" identifier="Bree-land_Adventurer_(advanced)"/>
<resource value="1879071678" identifier="Bree-land_Adventurer_(Final)"/>
<resource value="1879071679" identifier="Tales_of_the_Lonely_Road"/>
<resource value="1879071680" identifier="Tales_of_the_Lonely_Road_(advanced)"/>
<resource value="1879071681" identifier="Tales_of_the_Lonely_Road_(Final)"/>
<resource value="1879071682" identifier="Of_Glories_Long_Past"/>
<resource value="1879071683" identifier="Of_Glories_Long_Past_(advanced)"/>
<resource value="1879071684" identifier="Of_Glories_Long_Past_(Final)"/>
<resource value="1879071685" identifier="Restoring_the_Quick_Post"/>
<resource value="1879071686" identifier="Ally_of_Ered_Luin"/>
<resource value="1879071687" identifier="Defender_of_Ered_Luin"/>
<resource value="1879071688" identifier="Hero_of_Ered_Luin"/>
<resource value="1879071689" identifier="Marching_into_Shadow"/>
<resource value="1879071690" identifier="Marching_into_Shadow_(Advanced)"/>
<resource value="1879071691" identifier="Marching_into_Shadow_(Final)"/>
<resource value="1879071692" identifier="Deeds_in_the_Wilderness"/>
<resource value="1879071693" identifier="Deeds_in_the_Wilderness_(advanced)"/>
<resource value="1879071694" identifier="Deeds_in_the_Wilderness_(final)"/>
<resource value="1879071695" identifier="Peril_of_the_Mountains"/>
<resource value="1879071696" identifier="Peril_of_the_Mountains_(advanced)"/>
<resource value="1879071697" identifier="Peril_of_the_Mountains_(final)"/>
<resource value="1879071698" identifier="Barghest-slayer_(Bree-land)"/>
<resource value="1879071699" identifier="Barghest-slayer_(Advanced)_(Bree-land)"/>
<resource value="1879071700" identifier="Brigand-slayer_(Bree-land)"/>
<resource value="1879071701" identifier="Brigand-slayer_(Advanced)_(Bree-land)"/>
<resource value="1879071702" identifier="Bree-land_Woodsman_(Bree-land)"/>
<resource value="1879071703" identifier="Bree-land_Woodsman_(Advanced)_(Bree-land)"/>
<resource value="1879071704" identifier="Neekerbreeker-slayer_(Bree-land)"/>
<resource value="1879071705" identifier="Neekerbreeker-slayer_(Advanced)_(Bree-land)"/>
<resource value="1879071706" identifier="Orc-slayer_(Bree-land)"/>
<resource value="1879071707" identifier="Orc-slayer_(Advanced)_(Bree-land)"/>
<resource value="1879071708" identifier="Sickle-fly_Slayer_(Bree-land)"/>
<resource value="1879071710" identifier="Spider-slayer_(Bree-land)"/>
<resource value="1879071711" identifier="Spider-slayer_(Advanced)_(Bree-land)"/>
<resource value="1879071712" identifier="Wight-slayer_(Bree-land)"/>
<resource value="1879071713" identifier="Wight-slayer_(Advanced)_(Bree-land)"/>
<resource value="1879071714" identifier="Bog-lurker_Slayer_(Lone-lands)"/>
<resource value="1879071715" identifier="Bog-lurker_Slayer_(Advanced)_(Lone-lands)"/>
<resource value="1879071716" identifier="Wight-slayer_(Lone-lands)"/>
<resource value="1879071717" identifier="Wight-slayer_(Advanced)_(Lone-lands)"/>
<resource value="1879071718" identifier="Goblin-slayer_(Lone-lands)"/>
<resource value="1879071719" identifier="Goblin-slayer_(Advanced)_(Lone-lands)"/>
<resource value="1879071720" identifier="Orc-slayer_(Lone-lands)"/>
<resource value="1879071721" identifier="Orc-slayer_(Advanced)_(Lone-lands)"/>
<resource value="1879071722" identifier="Spider-slayer_(Lone-lands)"/>
<resource value="1879071723" identifier="Spider-slayer_(Advanced)_(Lone-lands)"/>
<resource value="1879071724" identifier="Warg-slayer_(Lone-lands)"/>
<resource value="1879071726" identifier="Goblin-slayer_(North_Downs)"/>
<resource value="1879071727" identifier="Goblin-slayer_(Advanced)_(North_Downs)"/>
<resource value="1879071728" identifier="Orc-slayer_(North_Downs)"/>
<resource value="1879071729" identifier="Orc-slayer_(Advanced)_(North_Downs)"/>
<resource value="1879071734" identifier="Warg-slayer_(North_Downs)"/>
<resource value="1879071735" identifier="Warg-slayer_(Advanced)_(North_Downs)"/>
<resource value="1879071736" identifier="Worm-slayer_(North_Downs)"/>
<resource value="1879071737" identifier="Worm-slayer_(Advanced)_(North_Downs)"/>
<resource value="1879071738" identifier="Brigand-slayer_(Shire)"/>
<resource value="1879071739" identifier="Brigand-slayer_(Advanced)_(Shire)"/>
<resource value="1879071740" identifier="Goblin-slayer_(Shire)"/>
<resource value="1879071741" identifier="Goblin-slayer_(Advanced)_(Shire)"/>
<resource value="1879071742" identifier="Harvest-fly_Slayer_(Shire)"/>
<resource value="1879071744" identifier="Slug-slayer_(Shire)"/>
<resource value="1879071745" identifier="Slug-slayer_(Advanced)_(Shire)"/>
<resource value="1879071746" identifier="Spider-slayer_(Shire)"/>
<resource value="1879071747" identifier="Spider-slayer_(Advanced)_(Shire)"/>
<resource value="1879071748" identifier="Wolf-slayer_(Shire)"/>
<resource value="1879071749" identifier="Wolf-slayer_(Advanced)_(Shire)"/>
<resource value="1879071750" identifier="Brigand-slayer_(Ered_Luin)"/>
<resource value="1879071751" identifier="Brigand-slayer_(Advanced)_(Ered_Luin)"/>
<resource value="1879071752" identifier="Goblin-slayer_(Ered_Luin)"/>
<resource value="1879071753" identifier="Goblin-slayer_(Advanced)_(Ered_Luin)"/>
<resource value="1879071754" identifier="Hendroval-slayer_(Ered_Luin)"/>
<resource value="1879071755" identifier="Hendroval-slayer_(Advanced)_(Ered_Luin)"/>
<resource value="1879071756" identifier="Spider-slayer_(Ered_Luin)"/>
<resource value="1879071757" identifier="Spider-slayer_(Advanced)_(Ered_Luin)"/>
<resource value="1879071758" identifier="Wolf-slayer_(Ered_Luin)"/>
<resource value="1879071759" identifier="Wolf-slayer_(Advanced)_(Ered_Luin)"/>
<resource value="1879071760" identifier="Angmarim-slayer_(Angmar)"/>
<resource value="1879071761" identifier="Angmarim-slayer_(Advanced)_(Angmar)"/>
<resource value="1879071762" identifier="Orc-slayer_(Angmar)"/>
<resource value="1879071763" identifier="Orc-slayer_(Advanced)_(Angmar)"/>
<resource value="1879071764" identifier="Troll-slayer_(Angmar)"/>
<resource value="1879071765" identifier="Troll-slayer_(Advanced)_(Angmar)"/>
<resource value="1879071768" identifier="Warg-slayer_(Angmar)"/>
<resource value="1879071769" identifier="Warg-slayer_(Advanced)_(Angmar)"/>
<resource value="1879071772" identifier="Worm-slayer_(Angmar)"/>
<resource value="1879071773" identifier="Worm-slayer_(Advanced)_(Angmar)"/>
<resource value="1879071776" identifier="Giant-slayer_(Misty_Mountains)"/>
<resource value="1879071777" identifier="Giant-slayer_(Advanced)_(Misty_Mountains)"/>
<resource value="1879071778" identifier="Snow-beast_Slayer_(Misty_Mountains)"/>
<resource value="1879071779" identifier="Snow-beast-slayer_(Advanced)_(Misty_Mountains)"/>
<resource value="1879071780" identifier="Troll-slayer_(Misty_Mountains)"/>
<resource value="1879071781" identifier="Troll-slayer_(Advanced)_(Misty_Mountains)"/>
<resource value="1879071782" identifier="Warg-slayer_(Misty_Mountains)"/>
<resource value="1879071783" identifier="Warg-slayer_(Advanced)_(Misty_Mountains)"/>
<resource value="1879071784" identifier="Worm-slayer_(Misty_Mountains)"/>
<resource value="1879071785" identifier="Worm-slayer_(Advanced)_(Misty_Mountains)"/>
<resource value="1879071786" identifier="Crawler-slayer_(Trollshaws)"/>
<resource value="1879071787" identifier="Crawler-slayer_(Advanced)_(Trollshaws)"/>
<resource value="1879071790" identifier="Troll-slayer_(Trollshaws)"/>
<resource value="1879071791" identifier="Troll-slayer_(Advanced)_(Trollshaws)"/>
<resource value="1879071792" identifier="Wight-slayer_(Trollshaws)"/>
<resource value="1879071793" identifier="Wight-slayer_(Advanced)_(Trollshaws)"/>
<resource value="1879071794" identifier="Wolf-slayer_(Trollshaws)"/>
<resource value="1879071795" identifier="Wolf-slayer_(Advanced)_(Trollshaws)"/>
<resource value="1879071796" identifier="Worm-slayer_(Trollshaws)"/>
<resource value="1879071797" identifier="Worm-slayer_(Advanced)_(Trollshaws)"/>
<resource value="1879071839" identifier="Shire_Brew-master"/>
<resource value="1879073460" identifier="Enmity_of_the_Wolves_(Race_&amp;_Social)"/>
<resource value="1879073461" identifier="Enmity_of_the_Wolves_II_(Race_&amp;_Social)"/>
<resource value="1879073462" identifier="Enmity_of_the_Wolves_III_(Race_&amp;_Social)"/>
<resource value="1879073463" identifier="Enmity_of_the_Spiders_(Race_&amp;_Social)"/>
<resource value="1879073464" identifier="Enmity_of_the_Spiders_II_(Race_&amp;_Social)"/>
<resource value="1879073465" identifier="Enmity_of_the_Spiders_III_(Race_&amp;_Social)"/>
<resource value="1879073466" identifier="Enmity_of_the_Goblins_(Race_&amp;_Social)"/>
<resource value="1879073467" identifier="Enmity_of_the_Goblins_II_(Race_&amp;_Social)"/>
<resource value="1879073506" identifier="Enmity_of_the_Dead_(Race_&amp;_Social)"/>
<resource value="1879073507" identifier="Enmity_of_the_Dead_II_(Race_&amp;_Social)"/>
<resource value="1879073508" identifier="Enmity_of_the_Dead_III_(Race_&amp;_Social)"/>
<resource value="1879073509" identifier="Enmity_of_the_Wargs_(Race_&amp;_Social)"/>
<resource value="1879073510" identifier="Enmity_of_the_Wargs_II_(Race_&amp;_Social)"/>
<resource value="1879073511" identifier="Enmity_of_the_Wargs_III_(Race_&amp;_Social)"/>
<resource value="1879073512" identifier="Enmity_of_the_Hillmen_(Race_&amp;_Social)"/>
<resource value="1879073513" identifier="Enmity_of_the_Hillmen_II_(Race_&amp;_Social)"/>
<resource value="1879073586" identifier="Enmity_of_the_Dourhands_(Race_&amp;_Social)"/>
<resource value="1879073587" identifier="Enmity_of_the_Dourhands_II_(Race_&amp;_Social)"/>
<resource value="1879073588" identifier="Enmity_of_the_Dourhands_III_(Race_&amp;_Social)"/>
<resource value="1879073589" identifier="Enmity_of_the_Goblins_(Race_&amp;_Social)"/>
<resource value="1879073590" identifier="Enmity_of_the_Goblins_II_(Race_&amp;_Social)"/>
<resource value="1879073591" identifier="Enmity_of_the_Goblins_III_(Race_&amp;_Social)"/>
<resource value="1879073592" identifier="Enmity_of_the_Trolls_(Race_&amp;_Social)"/>
<resource value="1879073593" identifier="Enmity_of_the_Trolls_II_(Race_&amp;_Social)"/>
<resource value="1879084435" identifier="Bastions_of_Hope"/>
<resource value="1879085025" identifier="The_Circle_of_Despair"/>
<resource value="1879086558" identifier="The_Shadows_of_Angmar"/>
<resource value="1879086561" identifier="Wanderer_of_Evendim"/>
<resource value="1879086562" identifier="Pilgrim_of_Evendim"/>
<resource value="1879086563" identifier="Warden_of_Evendim"/>
<resource value="1879086861" identifier="Tomb-defender_(Evendim)"/>
<resource value="1879086862" identifier="Tomb-defender_(Advanced)_(Evendim)"/>
<resource value="1879086869" identifier="Goblin-slayer_(Evendim)"/>
<resource value="1879086870" identifier="Goblin-slayer_(Advanced)_(Evendim)"/>
<resource value="1879086871" identifier="Kergrim-slayer_(Evendim)"/>
<resource value="1879086872" identifier="Kergrim-slayer_(Advanced)_(Evendim)"/>
<resource value="1879086873" identifier="Salamander-slayer_(Evendim)"/>
<resource value="1879086874" identifier="Salamander-slayer_(Advanced)_(Evendim)"/>
<resource value="1879089144" identifier="Tombs_of_Evendim"/>
<resource value="1879089145" identifier="Ruins_of_Evendim"/>
<resource value="1879089146" identifier="Wilds_of_Evendim"/>
<resource value="1879093958" identifier="Executioner_of_the_Wicked_(Bree-land)"/>
<resource value="1879093959" identifier="Nemesis_of_the_Fallen_(Bree-land)"/>
<resource value="1879093961" identifier="Brood-hunter_(Bree-land)"/>
<resource value="1879093962" identifier="Brood-hunter_(Advanced)_(Bree-land)"/>
<resource value="1879093963" identifier="Grave-digger_(Bree-land)"/>
<resource value="1879093965" identifier="Master_of_Beasts_(Ered_Luin)"/>
<resource value="1879093966" identifier="Master_of_Beasts_(Advanced)_(Ered_Luin)"/>
<resource value="1879093967" identifier="Betrayer%27s_Bane_(Ered_Luin)"/>
<resource value="1879093970" identifier="Troll-kicker_(Ered_Luin)"/>
<resource value="1879093971" identifier="Troll-kicker_(Advanced)_(Ered_Luin)"/>
<resource value="1879094069" identifier=""/>
<resource value="1879099039" identifier="The_Forbidding_Heights"/>
<resource value="1879099040" identifier="Goblin-town"/>
<resource value="1879099041" identifier="The_Wilds_of_T%C3%A2l_Bruinen"/>
<resource value="1879099095" identifier="Bilbo%27s_Buttons"/>
<resource value="1879099329" identifier="Craban-slayer_(Lone-lands)"/>
<resource value="1879099330" identifier="Craban-slayer_(Advanced)_(Lone-lands)"/>
<resource value="1879099331" identifier="Troll-slayer_(Lone-lands)"/>
<resource value="1879099332" identifier="Troll-slayer_(Advanced)_(Lone-lands)"/>
<resource value="1879101991" identifier="The_Shadows_of_Angmar_-_Part_II"/>
<resource value="1879107438" identifier="Inn_League_Challenge"/>
<resource value="1879107439" identifier="Inn_League_Member"/>
<resource value="1879109787" identifier="Ancient_Stones_of_Forochel"/>
<resource value="1879109788" identifier="Forochel_Expeditionary"/>
<resource value="1879109789" identifier="Forochel_Survivor"/>
<resource value="1879109790" identifier="Forochel_Pioneer"/>
<resource value="1879109791" identifier="Angmarim-slayer_(Forochel)"/>
<resource value="1879109801" identifier="Worm-slayer_(Forochel)"/>
<resource value="1879109802" identifier="Worm-slayer_(Advanced)_(Forochel)"/>
<resource value="1879110246" identifier="The_Lost_Fellowship"/>
<resource value="1879114242" identifier="The_Trolls_of_Urugarth_(Shadows_of_Angmar)"/>
<resource value="1879114243" identifier="The_Trolls_of_Urugarth_(Advanced)_(Shadows_of_Angmar)"/>
<resource value="1879114244" identifier="The_Beasts_of_Urugarth_(Shadows_of_Angmar)"/>
<resource value="1879114260" identifier="The_City_of_Orcs"/>
<resource value="1879114556" identifier="Ancient_Evil_of_Carn_D%C3%BBm_(Advanced)_(Shadows_of_Angmar)"/>
<resource value="1879114560" identifier="The_Trolls_of_Carn_D%C3%BBm_(Advanced)_(Shadows_of_Angmar)"/>
<resource value="1879114563" identifier="Champions_of_Carn_D%C3%BBm_(Shadows_of_Angmar)"/>
<resource value="1879114565" identifier="The_Angmarim_of_Carn_D%C3%BBm_(Advanced)_(Shadows_of_Angmar)"/>
<resource value="1879114574" identifier="The_Trolls_of_Carn_D%C3%BBm_(Shadows_of_Angmar)"/>
<resource value="1879114576" identifier="The_Orcs_of_Carn_D%C3%BBm_(Shadows_of_Angmar)"/>
<resource value="1879114580" identifier="The_Slugs_of_Carn_D%C3%BBm_(Shadows_of_Angmar)"/>
<resource value="1879115172" identifier="Invaders_from_Angmar_(Evendim)"/>
<resource value="1879115173" identifier="Invaders_from_Angmar_(Advanced)_(Evendim)"/>
<resource value="1879115174" identifier="Leaders_of_the_Invasion_(Evendim)"/>
<resource value="1879115177" identifier="Brutes_from_the_North_(Evendim)"/>
<resource value="1879115179" identifier="The_City_of_the_Kings"/>
<resource value="1879115181" identifier="Markers_of_the_Sunken_City"/>
<resource value="1879138809" identifier="Battle-master"/>
<resource value="1879138813" identifier="Relentless_Optimism"/>
<resource value="1879138824" identifier="Enduring_Morale"/>
<resource value="1879138825" identifier="Flow_of_Harmony"/>
<resource value="1879138826" identifier="Improved_Herald%27s_Strike"/>
<resource value="1879138827" identifier="Lyrics_of_Bravery"/>
<resource value="1879138828" identifier="Improved_Echoes_of_Battle"/>
<resource value="1879138829" identifier="Improved_Raise_the_Spirit"/>
<resource value="1879138830" identifier="Improved_Song_of_Soothing"/>
<resource value="1879138831" identifier="Power_of_Song"/>
<resource value="1879138840" identifier="The_Study_of_Frost-lore"/>
<resource value="1879138841" identifier="Improved_Sign_of_Power%3A_Command"/>
<resource value="1879138842" identifier="The_Secret_of_Tar"/>
<resource value="1879138843" identifier="The_Study_of_Fire-lore"/>
<resource value="1879138844" identifier="The_Study_of_Wind-lore"/>
<resource value="1879138845" identifier="Improved_Sign_of_Battle"/>
<resource value="1879138846" identifier="Improved_Storm-lore"/>
<resource value="1879138847" identifier="Improved_Inner_Flame"/>
<resource value="1879138856" identifier="Blocking_Force"/>
<resource value="1879138857" identifier="Hit_Where_It_Hurts"/>
<resource value="1879138858" identifier="Raw_Power"/>
<resource value="1879138859" identifier="Final_Straw"/>
<resource value="1879138860" identifier="Litany_of_Challenge"/>
<resource value="1879138861" identifier="Quick_of_Foot"/>
<resource value="1879138862" identifier="Shield_of_Fire"/>
<resource value="1879138863" identifier="Threatening_Presence"/>
<resource value="1879138872" identifier="Cruel_Odds"/>
<resource value="1879138873" identifier="Even_the_Odds"/>
<resource value="1879138874" identifier="Honed_Wit"/>
<resource value="1879138875" identifier="Sharp_Wit%2C_Sharp_Blade"/>
<resource value="1879138876" identifier="Spatial_Sense"/>
<resource value="1879138877" identifier="Strategic_Planning"/>
<resource value="1879138878" identifier="Complicated_Terms"/>
<resource value="1879138888" identifier="Heart_of_the_Bard"/>
<resource value="1879138889" identifier="Barbed_Hindrance"/>
<resource value="1879138890" identifier="Combat_Traps"/>
<resource value="1879138891" identifier="Critical_Eye"/>
<resource value="1879138892" identifier="Shot_through_the_Heart"/>
<resource value="1879138893" identifier="Strong_Intimidation"/>
<resource value="1879138894" identifier="The_Quality_of_Mercy"/>
<resource value="1879138895" identifier="Resolute_Aim"/>
<resource value="1879139153" identifier="Master_of_Connotation"/>
<resource value="1879139154" identifier="Linnod_of_Peace"/>
<resource value="1879139155" identifier="Master_of_Tragedy"/>
<resource value="1879139156" identifier="Frost-burn"/>
<resource value="1879139157" identifier="Overflowing_Confidence"/>
<resource value="1879139158" identifier="Confounding_Principles"/>
<resource value="1879139159" identifier="Linnod_of_Subtlety"/>
<resource value="1879139160" identifier="The_Prophetic_Word"/>
<resource value="1879139161" identifier="Tale_of_Rage"/>
<resource value="1879139162" identifier="Conflagration_of_Runes"/>
<resource value="1879139163" identifier="Scathing_Retort"/>
<resource value="1879139164" identifier="Writ_of_Blazing_Fire"/>
<resource value="1879139165" identifier="Icy_Discourse"/>
<resource value="1879139166" identifier="Terse_Narrative"/>
<resource value="1879139167" identifier="Memorable_Prose"/>
<resource value="1879139168" identifier="Rune_of_Endurance"/>
<resource value="1879139169" identifier="Author_of_Exaltation"/>
<resource value="1879139170" identifier="Master_of_Allusion"/>
<resource value="1879139171" identifier="Harsh_Debate"/>
<resource value="1879139172" identifier="Closing_Remarks"/>
<resource value="1879139173" identifier="Thunderous_Words"/>
<resource value="1879139174" identifier="Winter-storm"/>
<resource value="1879139434" identifier="The_Mines_of_Moria_(Epic)_(Burglar)"/>
<resource value="1879139435" identifier="The_Path_of_the_Mischief-maker"/>
<resource value="1879139436" identifier="A_Guide_to_the_Quiet_Knife"/>
<resource value="1879139443" identifier="The_Mines_of_Moria_(Epic)_(Guardian)"/>
<resource value="1879139444" identifier="The_Path_of_Freedom%27s_Defender"/>
<resource value="1879139445" identifier="A_Keen_Blade"/>
<resource value="1879139446" identifier="The_Mines_of_Moria_(Epic)_(Hunter)"/>
<resource value="1879139447" identifier="The_Path_of_the_Foe-trapper"/>
<resource value="1879139448" identifier="The_Jolly_Hunter"/>
<resource value="1879139449" identifier="The_Mines_of_Moria_(Epic)_(Loremaster)"/>
<resource value="1879139450" identifier="The_Path_of_the_Ancient_Master"/>
<resource value="1879139451" identifier="The_Book_of_Nature"/>
<resource value="1879139452" identifier="The_Mines_of_Moria_(Epic)_(Minstrel)"/>
<resource value="1879139453" identifier="The_Path_of_the_Resolve-watcher"/>
<resource value="1879139454" identifier="The_Verses_of_the_North"/>
<resource value="1879139455" identifier="The_Mines_of_Moria_(Epic)_(Rune-keeper)"/>
<resource value="1879139456" identifier="The_Path_of_the_Restoring_Rune"/>
<resource value="1879139457" identifier="On_the_Patterns_of_Wind_and_Rain"/>
<resource value="1879139459" identifier="The_Path_of_the_Masterful_Fist"/>
<resource value="1879140051" identifier="The_Great_Delving"/>
<resource value="1879140055" identifier="Orc-slayer_(Moria)"/>
<resource value="1879140056" identifier="Orc-slayer_(Advanced)_(Moria)"/>
<resource value="1879140605" identifier="The_Ring_Goes_South"/>
<resource value="1879140606" identifier="Silent_and_Restless"/>
<resource value="1879140607" identifier="Silent_and_Restless_(Intermediate)"/>
<resource value="1879140608" identifier="Silent_and_Restless_(Advanced)"/>
<resource value="1879140609" identifier="Silent_and_Restless_(Final)"/>
<resource value="1879140610" identifier="Craban-slayer_(Eregion)"/>
<resource value="1879140611" identifier="Craban-slayer_(Advanced)_(Eregion)"/>
<resource value="1879140612" identifier="Dunlending-slayer_(Eregion)"/>
<resource value="1879140613" identifier="Dunlending-slayer_(Advanced)_(Eregion)"/>
<resource value="1879140614" identifier="Half-orc_Slayer_(Eregion)"/>
<resource value="1879140615" identifier="Half-orc_Slayer_(Advanced)_(Eregion)"/>
<resource value="1879140616" identifier="Uruk-captains_of_Eregion_(Eregion)"/>
<resource value="1879140617" identifier="Lizard_and_Crawler-slayer_(Eregion)"/>
<resource value="1879140618" identifier="Lizard_and_Crawler-slayer_(Advanced)_(Eregion)"/>
<resource value="1879140619" identifier="Wolf_and_Warg-slayer_(Eregion)"/>
<resource value="1879140620" identifier="Wolf_and_Warg-slayer_(Advanced)_(Eregion)"/>
<resource value="1879141031" identifier="The_Flaming_Deeps"/>
<resource value="1879141032" identifier="The_Redhorn_Lodes"/>
<resource value="1879141033" identifier="Zelem-melek"/>
<resource value="1879141034" identifier="Eastern_Durin%27s_Way"/>
<resource value="1879141035" identifier="Western_Durin%27s_Way"/>
<resource value="1879141036" identifier="Nud-melek"/>
<resource value="1879141037" identifier="The_Water-works"/>
<resource value="1879141038" identifier="The_Foundations_of_Stone"/>
<resource value="1879141039" identifier="The_Silvertine_Lodes"/>
<resource value="1879141040" identifier="Deep-claw_Slayer_(Moria)"/>
<resource value="1879141041" identifier="Deep-claw_Slayer_(Advanced)_(Moria)"/>
<resource value="1879141042" identifier="Dragonet-slayer_(Moria)"/>
<resource value="1879141043" identifier="Dragonet-slayer_(Advanced)_(Moria)"/>
<resource value="1879141044" identifier="Globsnaga-slayer_(Moria)"/>
<resource value="1879141046" identifier="Goblin-slayer_(Moria)"/>
<resource value="1879141047" identifier="Goblin-slayer_(Advanced)_(Moria)"/>
<resource value="1879141048" identifier="Grodbog-slayer_(Moria)"/>
<resource value="1879141049" identifier="Grodbog-slayer_(Advanced)_(Moria)"/>
<resource value="1879141050" identifier="Morroval-slayer_(Moria)"/>
<resource value="1879141051" identifier="Morroval-slayer_(Advanced)_(Moria)"/>
<resource value="1879141052" identifier="Nameless-slayer_(Moria)"/>
<resource value="1879141053" identifier="Nameless-slayer_(Advanced)_(Moria)"/>
<resource value="1879141054" identifier="Spider-slayer_(Moria)"/>
<resource value="1879141055" identifier="Spider-slayer_(Advanced)_(Moria)"/>
<resource value="1879141058" identifier="Warg-slayer_(Moria)"/>
<resource value="1879144730" identifier="Thunder_and_Flame"/>
<resource value="1879144731" identifier="Golu_o_Maeth"/>
<resource value="1879144732" identifier="Whispers_in_the_Dark"/>
<resource value="1879145248" identifier="Dens_of_the_Beasts"/>
<resource value="1879145250" identifier="The_Ruins_of_Eregion"/>
<resource value="1879145251" identifier="Ring-lore_of_Eregion"/>
<resource value="1879145427" identifier="Invaders_of_Tham_M%C3%ADrdain_(Library)_(Shadows_of_Angmar)"/>
<resource value="1879145428" identifier="Invaders_of_Tham_M%C3%ADrdain_(School)_(Shadows_of_Angmar)"/>
<resource value="1879145429" identifier="Invaders_of_Tham_M%C3%ADrdain_(Ring-forge)_(Shadows_of_Angmar)"/>
<resource value="1879145430" identifier="Invaders_of_Tham_M%C3%ADrdain_(Complete)_(Shadows_of_Angmar)"/>
<resource value="1879145431" identifier="Mercenaries_of_the_White-hand_(Shadows_of_Angmar)"/>
<resource value="1879145432" identifier="Mercenaries_of_the_White-hand_(Advanced)_(Shadows_of_Angmar)"/>
<resource value="1879145433" identifier="Soldiers_of_the_Enemy_(Shadows_of_Angmar)"/>
<resource value="1879145434" identifier="Soldiers_of_the_Enemy_(Advanced)_(Shadows_of_Angmar)"/>
<resource value="1879145435" identifier="Warriors_of_the_Enemy_(Shadows_of_Angmar)"/>
<resource value="1879145436" identifier="Warriors_of_the_Enemy_(Advanced)_(Shadows_of_Angmar)"/>
<resource value="1879145439" identifier="The_Pale_Followers_(Shadows_of_Angmar)"/>
<resource value="1879145440" identifier="The_Pale_Followers_(Advanced)_(Shadows_of_Angmar)"/>
<resource value="1879145441" identifier="Lore_of_the_Forgotten_Library"/>
<resource value="1879145442" identifier="Texts_of_the_Crumbling_School"/>
<resource value="1879146126" identifier="Defilers_of_the_Forgotten_Treasury_(Mines_of_Moria)"/>
<resource value="1879146127" identifier="Defilers_of_the_Forgotten_Treasury_(Advanced)_(Mines_of_Moria)"/>
<resource value="1879146137" identifier="Treasures_of_the_Silvertine_Lodes"/>
<resource value="1879146138" identifier="Intruders_in_the_Vault_(Mines_of_Moria)"/>
<resource value="1879146845" identifier="The_Cliffs_of_Zirakzigil"/>
<resource value="1879146846" identifier="Bulwarks_of_the_Enemy"/>
<resource value="1879146847" identifier="In_the_Footsteps_of_the_Fellowship"/>
<resource value="1879146848" identifier="Explorer_of_Khazad-D%C3%BBm"/>
<resource value="1879146849" identifier="Worm-slayer_(Moria)"/>
<resource value="1879146850" identifier="Worm-slayer_(Advanced)_(Moria)"/>
<resource value="1879146868" identifier="Triumph_within_the_Deeps_(Moria)"/>
<resource value="1879147010" identifier="Implements_of_the_Forge"/>
<resource value="1879147011" identifier="Overseers_of_the_Forge_(Mines_of_Moria)"/>
<resource value="1879147012" identifier="Slaves_to_the_Forge_(Mines_of_Moria)"/>
<resource value="1879147018" identifier="Arms_of_the_Enemy"/>
<resource value="1879147023" identifier="Eyes_of_the_Enemy_(Advanced)_(Mines_of_Moria)"/>
<resource value="1879147025" identifier="Bane_of_Fil_Gashan_(Mines_of_Moria)"/>
<resource value="1879147026" identifier="Marshal_of_the_Burning_Depths_(Mines_of_Moria)"/>
<resource value="1879147151" identifier="Landings_of_the_Grand_Stair"/>
<resource value="1879147153" identifier="Letters_to_Igash"/>
<resource value="1879147154" identifier="Villains_of_the_Grand_Stair_(Part_1)_(Mines_of_Moria)"/>
<resource value="1879147155" identifier="Villains_of_the_Grand_Stair_(Part_2)_(Mines_of_Moria)"/>
<resource value="1879147156" identifier="Tamers_of_the_Vile_Wargs_(Mines_of_Moria)"/>
<resource value="1879147157" identifier="Tamers_of_the_Vile_Wargs_(Advanced)_(Mines_of_Moria)"/>
<resource value="1879147158" identifier="Followers_of_Igash_(Mines_of_Moria)"/>
<resource value="1879147159" identifier="Followers_of_Igash_(Advanced)_(Mines_of_Moria)"/>
<resource value="1879147164" identifier="The_Watcher_of_Moria"/>
<resource value="1879147165" identifier="Lost_to_the_Deeps"/>
<resource value="1879147166" identifier="The_Vile_Maw_(Mines_of_Moria)"/>
<resource value="1879147167" identifier="The_Arms_of_the_Watcher_(Mines_of_Moria)"/>
<resource value="1879147168" identifier="Arms_of_the_Watcher_(Advanced)_(Mines_of_Moria)"/>
<resource value="1879147170" identifier="Triumph_within_the_Forsaken_Deeps"/>
<resource value="1879147171" identifier="Runes_of_the_Dark_Delvings"/>
<resource value="1879147175" identifier="The_Corpse-eaters_(Mines_of_Moria)"/>
<resource value="1879147176" identifier="Leaders_of_the_Hive_(Mines_of_Moria)"/>
<resource value="1879147177" identifier="The_Hounds_of_Sk%C3%BBmfil_(Mines_of_Moria)"/>
<resource value="1879147178" identifier="The_Hounds_of_Sk%C3%BBmfil_(Advanced)_(Mines_of_Moria)"/>
<resource value="1879147179" identifier="The_Horrors_with_Many_Legs_(Mines_of_Moria)"/>
<resource value="1879147187" identifier="Nameless-slayer_(Mines_of_Moria)"/>
<resource value="1879147822" identifier="Investigating_the_Blight"/>
<resource value="1879147823" identifier="Corruption_in_Command_(Mines_of_Moria)"/>
<resource value="1879147824" identifier="Carriers_of_the_Blight_(Mines_of_Moria)"/>
<resource value="1879147826" identifier="Fallen_to_Blight_(Mines_of_Moria)"/>
<resource value="1879147828" identifier="Orcs_of_the_Sixteenth_Hall_(Mines_of_Moria)"/>
<resource value="1879149129" identifier="Deep_Delver"/>
<resource value="1879149130" identifier="Warrior_of_the_Shadows"/>
<resource value="1879149131" identifier="Legend_of_the_Deeps"/>
<resource value="1879149132" identifier="Wanderer_of_the_Central_Levels"/>
<resource value="1879149133" identifier="Stalwart_of_the_Central_Levels"/>
<resource value="1879149134" identifier="Exemplar_of_the_Central_Levels"/>
<resource value="1879149135" identifier="Adventurer_in_the_Upper_Levels"/>
<resource value="1879149136" identifier="Defender_of_the_Upper_Levels"/>
<resource value="1879149137" identifier="Hero_of_the_Upper_Levels"/>
<resource value="1879150855" identifier="D%C3%A2r_Narbugud_Fungus_Investigation"/>
<resource value="1879150860" identifier="Halls_of_Crafting_Melee_Orc-slayer_(Advanced)_(Scourge_of_Khazad-d%C3%BBm)"/>
<resource value="1879150863" identifier="Hierarchy_of_the_Nameless_(Scourge_of_Khazad-d%C3%BBm)"/>
<resource value="1879150864" identifier="D%C3%A2r_Narbugud_Nameless-slayer_(Scourge_of_Khazad-d%C3%BBm)"/>
<resource value="1879150865" identifier="D%C3%A2r_Narbugud_Nameless-slayer_(Advanced)_(Scourge_of_Khazad-d%C3%BBm)"/>
<resource value="1879150866" identifier="D%C3%A2r_Narbugud_Orc-slayer_(Scourge_of_Khazad-d%C3%BBm)"/>
<resource value="1879150867" identifier="D%C3%A2r_Narbugud_Orc-slayer_(Advanced)_(Scourge_of_Khazad-d%C3%BBm)"/>
<resource value="1879150868" identifier="D%C3%A2r_Narbugud_Troll-slayer_(Scourge_of_Khazad-d%C3%BBm)"/>
<resource value="1879152525" identifier=""/>
<resource value="1879152527" identifier="Wanderer_of_the_Golden_Wood"/>
<resource value="1879152528" identifier="City_of_the_Lord_and_Lady"/>
<resource value="1879152534" identifier="Friend_of_Lothl%C3%B3rien"/>
<resource value="1879152537" identifier="Orc-slayer_(Lothl%C3%B3rien)"/>
<resource value="1879152646" identifier="Ally_of_Lothl%C3%B3rien"/>
<resource value="1879152647" identifier="Defender_of_Lothl%C3%B3rien"/>
<resource value="1879152648" identifier="Warrior_of_Lothl%C3%B3rien"/>
<resource value="1879152682" identifier=""/>
<resource value="1879152683" identifier=""/>
<resource value="1879152741" identifier=""/>
<resource value="1879152743" identifier="An_Evil_Reflection_(Scourge_of_Khazad-d%C3%BBm)"/>
<resource value="1879154055" identifier="Flet-runner_Challenges"/>
<resource value="1879155755" identifier="Into_the_Black_and_Twisted_Forest"/>
<resource value="1879155756" identifier="Into_the_Black_and_Twisted_Forest_(Intermediate)"/>
<resource value="1879155757" identifier="Into_the_Black_and_Twisted_Forest_(Advanced)"/>
<resource value="1879155758" identifier="Dead-slayer_of_Southern_Mirkwood_(Southern_Mirkwood)"/>
<resource value="1879155759" identifier="Dead-slayer_(Advanced)_(Southern_Mirkwood)"/>
<resource value="1879155760" identifier="Orc_and_uruk-slayer_(Southern_Mirkwood)"/>
<resource value="1879155761" identifier="Orc_and_Uruk-slayer_(Advanced)_(Southern_Mirkwood)"/>
<resource value="1879155762" identifier="Spider-slayer_(Southern_Mirkwood)"/>
<resource value="1879155763" identifier="Spider-slayer_(Advanced)_(Southern_Mirkwood)"/>
<resource value="1879155766" identifier="Warg-slayer_(Southern_Mirkwood)"/>
<resource value="1879158107" identifier="Trouble_in_Tuckborough_(Skirmish_Instances)"/>
<resource value="1879159326" identifier="Celebrating_Sunshine"/>
<resource value="1879159790" identifier="Stand_at_Amon_S%C3%BBl_(Skirmish_Instances)"/>
<resource value="1879161030" identifier="Priestess_of_Flames_Slayer_(Skirmish_Lieutenant)"/>
<resource value="1879161037" identifier="Forest-born_Reaver_Slayer_(Advanced)_(Skirmish_Lieutenant)"/>
<resource value="1879161040" identifier="Tempest_of_Flame_Slayer_(Skirmish_Lieutenant)"/>
<resource value="1879161041" identifier="Dreadwing-marauder_Slayer_(Skirmish_Lieutenant)"/>
<resource value="1879161045" identifier="Thunderstone-smasher_Slayer_(Skirmish_Lieutenant)"/>
<resource value="1879161046" identifier="Primordial_Wrath_Slayer_(Skirmish_Lieutenant)"/>
<resource value="1879161048" identifier="Courage-breaker_Slayer_(Skirmish_Lieutenant)"/>
<resource value="1879161052" identifier="Venomous_Blood-arrow_Slayer_(Skirmish_Lieutenant)"/>
<resource value="1879161053" identifier="Bloodrook-slayer_(Advanced)_(Skirmish_Lieutenant)"/>
<resource value="1879161060" identifier="Rage_of_Morgoth_Slayer_(Skirmish_Lieutenant)"/>
<resource value="1879161061" identifier="Echo_of_Death_Slayer_(Skirmish_Lieutenant)"/>
<resource value="1879161067" identifier="Leadfoot_Brute_Slayer_(Skirmish_Lieutenant)"/>
<resource value="1879161085" identifier="Bearer_of_Blight_Slayer_(Advanced)_(Skirmish_Lieutenant)"/>
<resource value="1879161088" identifier="Fellbane_Archer_Slayer_(Skirmish_Lieutenant)"/>
<resource value="1879161093" identifier="Death-monger_Slayer_(Advanced)_(Skirmish_Lieutenant)"/>
<resource value="1879161100" identifier="Frigid_Squall_Slayer_(Skirmish_Lieutenant)"/>
<resource value="1879161101" identifier="Emissary_of_War_Slayer_(Skirmish_Lieutenant)"/>
<resource value="1879161108" identifier="Wretched_Falconer_Slayer_(Skirmish_Lieutenant)"/>
<resource value="1879161109" identifier="Bearer_of_Blight_Slayer_(Skirmish_Lieutenant)"/>
<resource value="1879161110" identifier="Daunting_Spirit-sapper_Slayer_(Skirmish_Lieutenant)"/>
<resource value="1879161111" identifier="Priest_of_Vengeance_Slayer_(Skirmish_Lieutenant)"/>
<resource value="1879161114" identifier="Daywalker-berserker_Slayer_(Skirmish_Lieutenant)"/>
<resource value="1879161118" identifier="Zealot_of_Pain_Slayer_(Skirmish_Lieutenant)"/>
<resource value="1879161120" identifier="Spawn_of_Angband_Slayer_(Skirmish_Lieutenant)"/>
<resource value="1879161125" identifier="Death-monger_Slayer_(Skirmish_Lieutenant)"/>
<resource value="1879161132" identifier="Enraged_Stonecrusher_Slayer_(Skirmish_Lieutenant)"/>
<resource value="1879161134" identifier="Zealot_of_Pain_Slayer_(Advanced)_(Skirmish_Lieutenant)"/>
<resource value="1879161135" identifier=""/>
<resource value="1879161137" identifier="Silent_Slayer_Stalker_(Skirmish_Lieutenant)"/>
<resource value="1879161138" identifier="Enraged_Snapper_Slayer_(Skirmish_Lieutenant)"/>
<resource value="1879161139" identifier="Forest-born_Reaver_Slayer_(Skirmish_Lieutenant)"/>
<resource value="1879161144" identifier="Crazed_Hate-monger_Slayer_(Skirmish_Lieutenant)"/>
<resource value="1879161146" identifier="Daywalker-berserker_Slayer_(Advanced)_(Skirmish_Lieutenant)"/>
<resource value="1879161150" identifier="Hulking_Pounder_Slayer_(Skirmish_Lieutenant)"/>
<resource value="1879161158" identifier="Bloodrook-slayer_(Skirmish_Lieutenant)"/>
<resource value="1879161163" identifier="Will-breaker_Slayer_(Skirmish_Lieutenant)"/>
<resource value="1879161166" identifier="Flesh-gorger_Slayer_(Skirmish_Lieutenant)"/>
<resource value="1879161177" identifier="Chaos-fiend_Slayer_(Skirmish_Lieutenant)"/>
<resource value="1879161178" identifier="Shepherd_of_Filth_Slayer_(Skirmish_Lieutenant)"/>
<resource value="1879161181" identifier="Vile_Defender_Slayer_(Skirmish_Lieutenant)"/>
<resource value="1879161183" identifier="Echo_of_Death_Slayer_(Advanced)_(Skirmish_Lieutenant)"/>
<resource value="1879161188" identifier="Raging_Marauder_Slayer_(Skirmish_Lieutenant)"/>
<resource value="1879161195" identifier="Brother_of_Destruction_Slayer_(Skirmish_Lieutenant)"/>
<resource value="1879161660" identifier="Protector_of_the_Vile_Slayer_(Skirmish_Lieutenant)"/>
<resource value="1879161975" identifier="Tutorial_Offensive%3A_Encounters_(Skirmish_Instances)"/>
<resource value="1879162646" identifier="Defence_of_The_Prancing_Pony_(Skirmish_Instances)"/>
<resource value="1879163154" identifier=""/>
<resource value="1879163163" identifier=""/>
<resource value="1879163164" identifier=""/>
<resource value="1879163166" identifier="Enter_the_Chambers_(Tower_of_Dol_Guldur)"/>
<resource value="1879163167" identifier="Throwing_Down_Sammath_G%C3%BBl"/>
<resource value="1879163168" identifier="Glory_in_the_Sword-hall_of_Dol_Guldur"/>
<resource value="1879163170" identifier="The_Spirits_are_the_Key"/>
<resource value="1879163171" identifier="The_Battle_of_the_Sword-hall_of_Dol_Guldur_(Tower_of_Dol_Guldur)"/>
<resource value="1879163174" identifier=""/>
<resource value="1879163176" identifier="Bringing_Down_the_Enemy"/>
<resource value="1879163178" identifier="Enter_the_Arena_(Tower_of_Dol_Guldur)"/>
<resource value="1879163181" identifier=""/>
<resource value="1879165716" identifier="Mirkwood_Landing"/>
<resource value="1879165717" identifier="Headcount_(Southern_Mirkwood)"/>
<resource value="1879173661" identifier="Strike_Against_Dannenglor_(Skirmish_Instances)"/>
<resource value="1879174910" identifier="Foe_of_the_Dead_--_Raid_(Skirmish_Instances)"/>
<resource value="1879174913" identifier="Foe_of_the_Dark_Lord_--_Raid_(Skirmish_Instances)"/>
<resource value="1879174918" identifier="Foe_of_the_Dead_--_Fellowship_(Skirmish_Instances)"/>
<resource value="1879174924" identifier="Foe_of_the_Dark_Lord_--_Fellowship_(Skirmish_Instances)"/>
<resource value="1879175096" identifier="Strength_of_Endurance_--_Fellowship"/>
<resource value="1879175101" identifier=""/>
<resource value="1879175103" identifier=""/>
<resource value="1879175106" identifier="Unvanquished_--_Raid"/>
<resource value="1879175107" identifier=""/>
<resource value="1879175111" identifier="Unvanquished_--_Fellowship"/>
<resource value="1879175115" identifier="Defeating_the_Dead_--_Raid"/>
<resource value="1879175116" identifier="Strength_of_Endurance_--_Raid"/>
<resource value="1879175117" identifier=""/>
<resource value="1879175120" identifier=""/>
<resource value="1879175122" identifier=""/>
<resource value="1879175129" identifier="Strength_in_Diversity_--_Fellowship"/>
<resource value="1879175134" identifier="Sorcerer-slayer_(Southern_Mirkwood)"/>
<resource value="1879175135" identifier="Sorcerer-slayer_(Advanced)_(Southern_Mirkwood)"/>
<resource value="1879175136" identifier="Beast-slayer_(Southern_Mirkwood)"/>
<resource value="1879175137" identifier="Beast-slayer_(Advanced)_(Southern_Mirkwood)"/>
<resource value="1879175326" identifier="Assault_on_the_Ringwraiths%27_Lair_(Skirmish_Instances)"/>
<resource value="1879175386" identifier="The_Wilds_of_Mirkwood"/>
<resource value="1879175387" identifier="Uncovering_the_Ruins_of_Mirkwood"/>
<resource value="1879175388" identifier="Evil_Strongholds_of_Mirkwood"/>
<resource value="1879176131" identifier="Troll_Wound-taker_Slayer_(Skirmish_Lieutenant)"/>
<resource value="1879176134" identifier="Dourhand_Storm-keeper_Slayer_(Skirmish_Lieutenant)"/>
<resource value="1879176136" identifier="Dourhand_Storm-keeper_Slayer_(Advanced)_(Skirmish_Lieutenant)"/>
<resource value="1879176139" identifier="Dourhand_Keg-master_Slayer_(Advanced)_(Skirmish_Lieutenant)"/>
<resource value="1879176144" identifier="Pale_Trapper_Slayer_(Skirmish_Lieutenant)"/>
<resource value="1879176147" identifier="Troll_Wound-taker_Slayer_(Advanced)_(Skirmish_Lieutenant)"/>
<resource value="1879176149" identifier="Pale_Trapper_Slayer_(Advanced)_(Skirmish_Lieutenant)"/>
<resource value="1879176150" identifier="Dourhand_Keg-master_Slayer_(Skirmish_Lieutenant)"/>
<resource value="1879178992" identifier="Smoke_Before_the_Fire"/>
<resource value="1879180376" identifier="Known_to_the_Eglain"/>
<resource value="1879180377" identifier="Friend_of_the_Eglain"/>
<resource value="1879180378" identifier="Ally_of_the_Eglain"/>
<resource value="1879180379" identifier="Eglan"/>
<resource value="1879180571" identifier="The_Siege_of_Mirkwood"/>
<resource value="1879182332" identifier="The_Shrewd_Gardener"/>
<resource value="1879182340" identifier="Spring_is_Dandy"/>
<resource value="1879183071" identifier="Ale_Association_Acquaintance"/>
<resource value="1879183122" identifier="Volume_III%3A_%27Allies_of_the_King%27_Foreword"/>
<resource value="1879184309" identifier="Hawk-Eyed_Harrier_Slayer_(Skirmish_Lieutenant)"/>
<resource value="1879185328" identifier="Helegrod_--_The_Gate_to_Thorog_(Shadows_of_Angmar)"/>
<resource value="1879185461" identifier="Inn_League_Delivery"/>
<resource value="1879185930" identifier="Ale_Association_Initiation"/>
<resource value="1879186733" identifier="Exploration_from_Top_to_Bottom"/>
<resource value="1879188417" identifier="The_Library_at_Tham_M%C3%ADrdain_(Shadows_of_Angmar)"/>
<resource value="1879188445" identifier="The_School_at_Tham_M%C3%ADrdain_(Shadows_of_Angmar)"/>
<resource value="1879188857" identifier="Helegrod_--_Drake_Wing_(Shadows_of_Angmar)"/>
<resource value="1879190071" identifier="Mysteries_of_Enedwaith"/>
<resource value="1879190074" identifier="Dunlending-slayer_(Enedwaith)"/>
<resource value="1879190075" identifier="Mysteries_of_Enedwaith_(Intermediate)"/>
<resource value="1879190076" identifier="Mysteries_of_Enedwaith_(Advanced)"/>
<resource value="1879190079" identifier="Mysteries_of_Enedwaith_(Final)"/>
<resource value="1879190082" identifier="Path_of_the_Grey_Company"/>
<resource value="1879190100" identifier="The_Cartrevs_of_Enedwaith"/>
<resource value="1879190115" identifier="Dunlending-slayer_(Advanced)_(Enedwaith)"/>
<resource value="1879190118" identifier="Half-orc_Slayer_(Enedwaith)"/>
<resource value="1879190119" identifier="Half-orc_Slayer_(Advanced)_(Enedwaith)"/>
<resource value="1879190120" identifier="Wood-troll_Slayer_(Enedwaith)"/>
<resource value="1879190121" identifier="Wood-troll_Slayer_(Advanced)_(Enedwaith)"/>
<resource value="1879190166" identifier="Great_Barrow_--_The_Gate_to_Sambrog_(Shadows_of_Angmar)"/>
<resource value="1879190348" identifier="Great_Barrow_--_Water_Wing_(Shadows_of_Angmar)"/>
<resource value="1879190349" identifier="Great_Barrow_--_Sambrog_Wing_(Shadows_of_Angmar)"/>
<resource value="1879190357" identifier="Known_to_the_Wardens_of_Ann%C3%BAminas"/>
<resource value="1879190358" identifier="Friend_to_the_Wardens_of_Ann%C3%BAminas"/>
<resource value="1879190359" identifier="Ally_to_the_Wardens_of_Ann%C3%BAminas"/>
<resource value="1879190360" identifier="Kindred_with_the_Wardens_of_Ann%C3%BAminas"/>
<resource value="1879190361" identifier="Known_to_the_Men_of_Bree"/>
<resource value="1879190362" identifier="Friend_to_the_Men_of_Bree"/>
<resource value="1879190363" identifier="Ally_to_the_Men_of_Bree"/>
<resource value="1879190364" identifier="Kindred_to_the_Men_of_Bree"/>
<resource value="1879190365" identifier="Known_to_Council_of_North"/>
<resource value="1879190366" identifier="Friend_of_the_Council_of_the_North"/>
<resource value="1879190369" identifier="Known_to_the_Rangers_of_Esteld%C3%ADn"/>
<resource value="1879190370" identifier="Friend_to_the_Rangers_of_Esteld%C3%ADn"/>
<resource value="1879190371" identifier="Ally_to_the_Rangers_of_Esteld%C3%ADn"/>
<resource value="1879190373" identifier="Known_to_the_Iron_Garrison_Guards"/>
<resource value="1879190374" identifier="Friend_to_the_Iron_Garrison_Guards"/>
<resource value="1879190375" identifier="Ally_to_the_Iron_Garrison_Guards"/>
<resource value="1879190376" identifier="Kindred_with_the_Iron_Garrison_Guards"/>
<resource value="1879190377" identifier="Known_to_the_Iron_Garrison_Miners"/>
<resource value="1879190378" identifier="Friend_to_the_Iron_Garrison_Miners"/>
<resource value="1879190379" identifier="Ally_to_the_Iron_Garrison_Miners"/>
<resource value="1879190380" identifier="Kindred_with_the_Iron_Garrison_Miners"/>
<resource value="1879190381" identifier="Known_to_the_Lossoth"/>
<resource value="1879190382" identifier="Friend_to_the_Lossoth"/>
<resource value="1879190383" identifier="Ally_to_the_Lossoth"/>
<resource value="1879190385" identifier="Known_to_the_Galadhrim"/>
<resource value="1879190386" identifier="Friend_to_the_Galadhrim"/>
<resource value="1879190387" identifier="Ally_to_the_Galadhrim"/>
<resource value="1879190388" identifier="Kindred_with_the_Galadhrim"/>
<resource value="1879190389" identifier="Known_to_the_Mathom_Society"/>
<resource value="1879190390" identifier="Friend_to_the_Mathom_Society"/>
<resource value="1879190391" identifier="Ally_of_the_Mathom_Society"/>
<resource value="1879190392" identifier="Kindred_with_the_Mathom_Society"/>
<resource value="1879190393" identifier="Known_to_the_Elves_of_Rivendell"/>
<resource value="1879190394" identifier="Friend_to_the_Elves_of_Rivendell"/>
<resource value="1879190395" identifier="Ally_to_the_Elves_of_Rivendell"/>
<resource value="1879190396" identifier="Kindred_with_the_Elves_of_Rivendell"/>
<resource value="1879190397" identifier="Known_to_Thorin%27s_Hall"/>
<resource value="1879190398" identifier="Friend_to_Thorin%27s_Hall"/>
<resource value="1879190399" identifier="Ally_of_Thorin%27s_Hall"/>
<resource value="1879190400" identifier="Kindred_to_Thorin%27s_Hall"/>
<resource value="1879190449" identifier="Kindred_with_the_Malledhrim"/>
<resource value="1879190451" identifier="Friend_to_the_Malledhrim"/>
<resource value="1879190454" identifier="Ally_to_the_Malledhrim"/>
<resource value="1879190455" identifier="Known_to_the_Malledhrim"/>
<resource value="1879190456" identifier="Known_to_the_Algraig"/>
<resource value="1879190470" identifier="Friend_to_the_Algraig"/>
<resource value="1879190471" identifier="Known_to_the_Grey_Company"/>
<resource value="1879190476" identifier="Ally_to_the_Grey_Company"/>
<resource value="1879190489" identifier="Friend_to_the_Grey_Company"/>
<resource value="1879190796" identifier="Master_of_Stairs"/>
<resource value="1879190797" identifier="Exiles_from_the_Lonely_Mountain"/>
<resource value="1879190838" identifier="Little_Wonders"/>
<resource value="1879192918" identifier="Gwiber-slayer_(Enedwaith)"/>
<resource value="1879192930" identifier="Gwiber_Slayer_(Advanced)_(Enedwaith)"/>
<resource value="1879192931" identifier="Giant-slayer_(Enedwaith)"/>
<resource value="1879192932" identifier="Giant_Slayer_(Advanced)_(Enedwaith)"/>
<resource value="1879196953" identifier=""/>
<resource value="1879196954" identifier=""/>
<resource value="1879196955" identifier=""/>
<resource value="1879197817" identifier="The_Up-and-Comer"/>
<resource value="1879197819" identifier="The_Go-getter"/>
<resource value="1879197820" identifier="The_Hot_Shot"/>
<resource value="1879197821" identifier="The_Busy_Bee"/>
<resource value="1879197822" identifier="The_Eager_Beaver"/>
<resource value="1879198509" identifier="Ambassador_to_the_Elves"/>
<resource value="1879198835" identifier=""/>
<resource value="1879201162" identifier=""/>
<resource value="1879201450" identifier=""/>
<resource value="1879201467" identifier=""/>
<resource value="1879201468" identifier=""/>
<resource value="1879201469" identifier=""/>
<resource value="1879201491" identifier=""/>
<resource value="1879201570" identifier=""/>
<resource value="1879201577" identifier=""/>
<resource value="1879201587" identifier=""/>
<resource value="1879201589" identifier=""/>
<resource value="1879201601" identifier=""/>
<resource value="1879201687" identifier=""/>
<resource value="1879201688" identifier=""/>
<resource value="1879201689" identifier=""/>
<resource value="1879201752" identifier=""/>
<resource value="1879204078" identifier=""/>
<resource value="1879204652" identifier=""/>
<resource value="1879204654" identifier=""/>
<resource value="1879204657" identifier=""/>
<resource value="1879205339" identifier=""/>
<resource value="1879205361" identifier=""/>
<resource value="1879205362" identifier=""/>
<resource value="1879205363" identifier=""/>
<resource value="1879205364" identifier=""/>
<resource value="1879205365" identifier=""/>
<resource value="1879205369" identifier=""/>
<resource value="1879205371" identifier=""/>
<resource value="1879205372" identifier=""/>
<resource value="1879205373" identifier=""/>
<resource value="1879205374" identifier=""/>
<resource value="1879205376" identifier=""/>
<resource value="1879205776" identifier=""/>
<resource value="1879205933" identifier=""/>
<resource value="1879205934" identifier=""/>
<resource value="1879205935" identifier=""/>
<resource value="1879206101" identifier=""/>
<resource value="1879206121" identifier=""/>
<resource value="1879206123" identifier="Mighty_Um%C3%ADn_(Shadows_of_Angmar)"/>
<resource value="1879206145" identifier=""/>
<resource value="1879206148" identifier=""/>
<resource value="1879209658" identifier=""/>
<resource value="1879210280" identifier=""/>
<resource value="1879212360" identifier="Quests_of_the_Great_Delving"/>
<resource value="1879212361" identifier="Quests_of_the_Silvertine_Lodes"/>
<resource value="1879212362" identifier="Quests_of_the_Water-works"/>
<resource value="1879212363" identifier="Quests_of_Durin%27s_Way"/>
<resource value="1879212365" identifier=""/>
<resource value="1879212366" identifier=""/>
<resource value="1879212367" identifier=""/>
<resource value="1879212368" identifier=""/>
<resource value="1879214991" identifier=""/>
<resource value="1879214992" identifier=""/>
<resource value="1879214993" identifier=""/>
<resource value="1879214994" identifier=""/>
<resource value="1879217868" identifier="Dunlending-Slayer"/>
<resource value="1879220072" identifier="Beast-Slayer"/>
<resource value="1879220073" identifier="Uruk-Hai_Slayer"/>
<resource value="1879220075" identifier=""/>
<resource value="1879220076" identifier=""/>
<resource value="1879220078" identifier="Slayer_of_the_Dead"/>
<resource value="1879220079" identifier=""/>
<resource value="1879220080" identifier="Dunlending-Slayer_(Advanced)"/>
<resource value="1879220081" identifier="Beast-Slayer_(Advanced)"/>
<resource value="1879220084" identifier=""/>
<resource value="1879220088" identifier=""/>
<resource value="1879220091" identifier=""/>
<resource value="1879220131" identifier=""/>
<resource value="1879220132" identifier=""/>
<resource value="1879220133" identifier=""/>
<resource value="1879220134" identifier=""/>
<resource value="1879220135" identifier=""/>
<resource value="1879220136" identifier=""/>
<resource value="1879220137" identifier=""/>
<resource value="1879220138" identifier=""/>
<resource value="1879220211" identifier=""/>
<resource value="1879220266" identifier=""/>
<resource value="1879220269" identifier=""/>
<resource value="1879220270" identifier=""/>
<resource value="1879220271" identifier=""/>
<resource value="1879220272" identifier=""/>
<resource value="1879220273" identifier=""/>
<resource value="1879220276" identifier=""/>
<resource value="1879220277" identifier=""/>
<resource value="1879220278" identifier=""/>
<resource value="1879220332" identifier=""/>
<resource value="1879220337" identifier=""/>
<resource value="1879221549" identifier=""/>
<resource value="1879221749" identifier=""/>
<resource value="1879222235" identifier=""/>
<resource value="1879222236" identifier=""/>
<resource value="1879222237" identifier=""/>
<resource value="1879222238" identifier=""/>
<resource value="1879222240" identifier=""/>
<resource value="1879222241" identifier=""/>
<resource value="1879222242" identifier=""/>
<resource value="1879222243" identifier=""/>
<resource value="1879226083" identifier="Commanders_of_the_Foundry%2C_Tier_I"/>
<resource value="1879226101" identifier="Commanders_of_the_Foundry%2C_Tier_II"/>
<resource value="1879226615" identifier="Challenge%3A_The_Foundry"/>
<resource value="1879226616" identifier="Isengard%3A_The_Foundry"/>
<resource value="1879227678" identifier="Tower_of_Orthanc%3A_Ring_of_Acid_--_Tier_1"/>
<resource value="1879227679" identifier="Tower_of_Orthanc%3A_Ring_of_Acid_--_Tier_2"/>
<resource value="1879227680" identifier="Tower_of_Orthanc%3A_Ring_of_Lightning_--_Tier_1"/>
<resource value="1879227681" identifier="Tower_of_Orthanc%3A_Ring_of_Lightning_--_Tier_2"/>
<resource value="1879227683" identifier="Tower_of_Orthanc%3A_Ring_of_Shadow_--_Tier_1"/>
<resource value="1879227684" identifier="Tower_of_Orthanc%3A_Rings_of_Fire_and_Frost_--_Tier_2"/>
<resource value="1879227685" identifier="Tower_of_Orthanc%3A_Rings_of_Fire_and_Frost_--_Tier_1"/>
<resource value="1879227688" identifier="Tower_of_Orthanc%3A_Saruman%27s_Ring_--_Tier_1"/>
<resource value="1879227701" identifier="Tower_of_Orthanc%3A_The_Mind_of_Saruman_--_Tier_1"/>
<resource value="1879227754" identifier="Tower_of_Orthanc%3A_Conductivity"/>
<resource value="1879227755" identifier="Tower_of_Orthanc%3A_Acid_Wash"/>
<resource value="1879227844" identifier="Commanders_of_Isengard_--_Tier_I"/>
<resource value="1879227845" identifier="Isengard%3A_Dargnkh_Unleashed"/>
<resource value="1879227846" identifier="Commanders_of_Isengard_--_Tier_II"/>
<resource value="1879227847" identifier="Challenge%3A_Dargnkh_Unleashed"/>
<resource value="1879227895" identifier="Save_the_Trees"/>
<resource value="1879227965" identifier="Discovery%3A_Instances_of_Isengard"/>
<resource value="1879227972" identifier="Thoroughbred"/>
<resource value="1879227973" identifier="Clear-cutter"/>
<resource value="1879227974" identifier="Last_Tree_Standing"/>
<resource value="1879228031" identifier="Isengard%3A_Fangorn%27s_Edge"/>
<resource value="1879228033" identifier="Abolish_Abominations"/>
<resource value="1879228034" identifier="End_the_Suffering"/>
<resource value="1879228035" identifier="Fire_to_Ashes"/>
<resource value="1879228036" identifier="Isengard%3A_The_Pits_of_Isengard"/>
</resources>
